setup.py
bi_ga_distribution/Binomialdistribution.py
bi_ga_distribution/Gaussiandistribution.py
bi_ga_distribution/Generaldistribution.py
bi_ga_distribution/__init__.py
bi_ga_distribution.egg-info/PKG-INFO
bi_ga_distribution.egg-info/SOURCES.txt
bi_ga_distribution.egg-info/dependency_links.txt
bi_ga_distribution.egg-info/not-zip-safe
bi_ga_distribution.egg-info/top_level.txt