Metadata-Version: 1.0
Name: bi-ga-distribution
Version: 0.1
Summary: Binomial and Gaussian distributions
Home-page: UNKNOWN
Author: Chen Chen
Author-email: chenc1416@gmail.com
License: UNKNOWN
Platform: UNKNOWN
